{
   "type":"recipe",

   "work_units"  : 3,
   "recipe_name" : "Yellow Comfy Bed",
   "description" : "Eight hours will leave you as refreshed as the day you were born.",
   "flavor"      : "Nobody ever wants to get out. It makes emergency evacuations awkward.",
   "portrait"    : "/colors-base/entities/furniture/comfy_bed/comfy_bed_yellow//comfy_bed_yellow.png",
   "level_requirement" : 2,

   "ingredients": [
      {
         "uri" : "stonehearth:furniture:not_much_of_a_bed",
         "count" : 1
      },
	  {
         "uri" : "colors-base:cloth_bolt_yellow",
         "count" : 1
      }
  ],
  "produces": [
      {
         "item":"colors-base:comfy_bed_yellow"
      }
  ]
}
